cryptodatapy_pandas_datareader-0.10.1.post1.dist-info/licenses/LICENSE.md
docs/contributors.py
docs/source/conf.py
pandas_datareader/__init__.py
pandas_datareader/_testing.py
pandas_datareader/_utils.py
pandas_datareader/_version.py
pandas_datareader/bankofcanada.py
pandas_datareader/base.py
pandas_datareader/conftest.py
pandas_datareader/data.py
pandas_datareader/econdb.py
pandas_datareader/enigma.py
pandas_datareader/eurostat.py
pandas_datareader/exceptions.py
pandas_datareader/famafrench.py
pandas_datareader/fred.py
pandas_datareader/moex.py
pandas_datareader/nasdaq_trader.py
pandas_datareader/naver.py
pandas_datareader/oecd.py
pandas_datareader/quandl.py
pandas_datareader/stooq.py
pandas_datareader/tiingo.py
pandas_datareader/tsp.py
pandas_datareader/wb.py
pandas_datareader/av/__init__.py
pandas_datareader/av/forex.py
pandas_datareader/av/quotes.py
pandas_datareader/av/sector.py
pandas_datareader/av/time_series.py
pandas_datareader/compat/__init__.py
pandas_datareader/iex/__init__.py
pandas_datareader/iex/daily.py
pandas_datareader/iex/deep.py
pandas_datareader/iex/market.py
pandas_datareader/iex/ref.py
pandas_datareader/iex/stats.py
pandas_datareader/iex/tops.py
pandas_datareader/io/__init__.py
pandas_datareader/io/jsdmx.py
pandas_datareader/io/sdmx.py
pandas_datareader/io/util.py
pandas_datareader/tests/__init__.py
pandas_datareader/tests/test_bankofcanada.py
pandas_datareader/tests/test_base.py
pandas_datareader/tests/test_data.py
pandas_datareader/tests/test_econdb.py
pandas_datareader/tests/test_enigma.py
pandas_datareader/tests/test_eurostat.py
pandas_datareader/tests/test_famafrench.py
pandas_datareader/tests/test_fred.py
pandas_datareader/tests/test_iex.py
pandas_datareader/tests/test_iex_daily.py
pandas_datareader/tests/test_moex.py
pandas_datareader/tests/test_nasdaq.py
pandas_datareader/tests/test_naver.py
pandas_datareader/tests/test_oecd.py
pandas_datareader/tests/test_quandl.py
pandas_datareader/tests/test_stooq.py
pandas_datareader/tests/test_tiingo.py
pandas_datareader/tests/test_tsp.py
cryptodatapy_pandas_datareader-0.10.1.post1.dist-info/METADATA
cryptodatapy_pandas_datareader-0.10.1.post1.dist-info/WHEEL
cryptodatapy_pandas_datareader-0.10.1.post1.dist-info/top_level.txt
cryptodatapy_pandas_datareader-0.10.1.post1.dist-info/RECORD
