Metadata-Version: 2.4
Name: cryptodatapy-pandas-datareader
Version: 0.10.1.post1
Summary: Pandas-compatible data readers. Formerly a component of pandas.
Author-email: The PyData Development Team <pydata@googlegroups.com>
License: =======
Project-URL: Homepage, https://pandas.pydata.org
Project-URL: Documentation, https://pandas-datareader.readthedocs.io/en/latest/
Project-URL: Repository, https://github.com/pydata/pandas-datareader.git
Project-URL: Bug Tracker, https://github.com/pydata/pandas-datareader/issues
Classifier: Development Status :: 5 - Production/Stable
Classifier: Environment :: Console
Classifier: Intended Audience :: Science/Research
Classifier: License :: OSI Approved :: BSD License
Classifier: Operating System :: OS Independent
Classifier: Programming Language :: Python
Classifier: Programming Language :: Python :: 3
Classifier: Programming Language :: Python :: 3 :: Only
Classifier: Programming Language :: Python :: 3.9
Classifier: Programming Language :: Python :: 3.10
Classifier: Programming Language :: Python :: 3.11
Classifier: Programming Language :: Python :: 3.12
Classifier: Programming Language :: Python :: 3.13
Classifier: Topic :: Scientific/Engineering
Requires-Python: >=3.9
License-File: LICENSE.md
Requires-Dist: lxml
Requires-Dist: pandas>=1.5.3
Requires-Dist: requests>=2.19.0
Dynamic: license-file
